honeybee_radiance_folder/__init__.py
honeybee_radiance_folder/cli.py
honeybee_radiance_folder/config.py
honeybee_radiance_folder/folder.cfg
honeybee_radiance_folder/folder.py
honeybee_radiance_folder/folderutil.py
honeybee_radiance_folder/gridutil.py
honeybee_radiance_folder-2.11.17.dist-info/licenses/LICENSE
honeybee_radiance_folder-2.11.17.dist-info/METADATA
honeybee_radiance_folder-2.11.17.dist-info/WHEEL
honeybee_radiance_folder-2.11.17.dist-info/entry_points.txt
honeybee_radiance_folder-2.11.17.dist-info/top_level.txt
honeybee_radiance_folder-2.11.17.dist-info/RECORD
