Metadata-Version: 2.4
Name: honeybee-radiance-folder
Version: 2.11.17
Summary: Honeybee Radiance folder is a Python library to read, write and validate Radiance folder structure.
Home-page: https://github.com/ladybug-tools/honeybee-radiance-folder
Author: Ladybug Tools
Author-email: info@ladybug.tools
Classifier: Programming Language :: Python :: 2.7
Classifier: Programming Language :: Python :: 3.7
Classifier: Programming Language :: Python :: 3.8
Classifier: Programming Language :: Python :: 3.9
Classifier: Programming Language :: Python :: 3.10
Classifier: Programming Language :: Python :: 3.11
Classifier: Programming Language :: Python :: 3.12
Classifier: Programming Language :: Python :: Implementation :: CPython
Classifier: Programming Language :: Python :: Implementation :: IronPython
Classifier: Operating System :: OS Independent
License-File: LICENSE
Provides-Extra: cli
Requires-Dist: click>=7.1.2; extra == "cli"
Dynamic: author
Dynamic: author-email
Dynamic: classifier
Dynamic: description
Dynamic: description-content-type
Dynamic: home-page
Dynamic: license-file
Dynamic: provides-extra
Dynamic: summary
